auto_po_lyglot/__init__.py
auto_po_lyglot/csv_extractor.py
auto_po_lyglot/default_prompts.py
auto_po_lyglot/django_po.py
auto_po_lyglot/getenv.py
auto_po_lyglot/po_django_main.py
auto_po_lyglot/po_main.py
auto_po_lyglot/po_streamlit.py
auto_po_lyglot/clients/__init__.py
auto_po_lyglot/clients/claude_client.py
auto_po_lyglot/clients/client_base.py
auto_po_lyglot/clients/gemini_client.py
auto_po_lyglot/clients/grok_client.py
auto_po_lyglot/clients/openai_ollama_client.py
auto_po_lyglot/auto_po_lyglot/__init__.py
auto_po_lyglot/auto_po_lyglot/csv_extractor.py
auto_po_lyglot/auto_po_lyglot/default_prompts.py
auto_po_lyglot/auto_po_lyglot/django_po.py
auto_po_lyglot/auto_po_lyglot/getenv.py
auto_po_lyglot/auto_po_lyglot/po_django_main.py
auto_po_lyglot/auto_po_lyglot/po_main.py
auto_po_lyglot/auto_po_lyglot/po_streamlit.py
auto_po_lyglot/auto_po_lyglot/clients/__init__.py
auto_po_lyglot/auto_po_lyglot/clients/claude_client.py
auto_po_lyglot/auto_po_lyglot/clients/client_base.py
auto_po_lyglot/auto_po_lyglot/clients/gemini_client.py
auto_po_lyglot/auto_po_lyglot/clients/grok_client.py
auto_po_lyglot/auto_po_lyglot/clients/openai_ollama_client.py
auto_po_lyglot-1.5.1.dist-info/METADATA
auto_po_lyglot-1.5.1.dist-info/WHEEL
auto_po_lyglot-1.5.1.dist-info/entry_points.txt
auto_po_lyglot-1.5.1.dist-info/licenses/LICENSE
auto_po_lyglot-1.5.1.dist-info/RECORD
