Metadata-Version: 2.3
Name: auto-po-lyglot
Version: 1.5.1
Summary: A Python package to translate po files using LLMs. Implements ChatGPT, Claude, Gemini, Grok and Ollama clients. Uses a 1rst manual translation for desambiguating short PO pieces of sentences.
Project-URL: Homepage, https://github.com/leolivier/transpo
Project-URL: Repository, https://github.com/leolivier/transpo.git
Project-URL: Issues, https://github.com/leolivier/transpo/issues
Project-URL: Download, https://github.com/leolivier/transpo/archive/refs/tags/v1.0.0.tar.gz
Author-email: Olivier LEVILLAIN <levillain.olivier@gmail.com>
License-File: LICENSE
Keywords: AI,llm,poet,python,translation
Classifier: Development Status :: 4 - Beta
Classifier: License :: OSI Approved :: MIT License
Classifier: Operating System :: OS Independent
Classifier: Programming Language :: Python :: 3
Requires-Python: >=3.10
Requires-Dist: anthropic>=0.34.1
Requires-Dist: google-generativeai>=0.7.2
Requires-Dist: langcodes>=3.4.0
Requires-Dist: openai>=1.12.0
Requires-Dist: polib>=1.2.0
Requires-Dist: python-dotenv>=1.0.1
Requires-Dist: streamlit>=1.38.0
Requires-Dist: xai-sdk>=0.3.0
